{
  "project_info": {
    "project_number": "960282246537",
    "project_id": "quizapp-2f205",
    "storage_bucket": "quizapp-2f205.appspot.com"
  },
  "client": [
    {
      "client_info": {
        "mobilesdk_app_id": "1:960282246537:android:685a0a760afd4c20a23558",
        "android_client_info": {
          "package_name": "com.example.quizapp"
        }
      },
      "oauth_client": [
        {
          "client_id": "960282246537-t5suv1qklqtea5rghe84lgd9od608a3r.apps.googleusercontent.com",
          "client_type": 3
        }
      ],
      "api_key": [
        {
          "current_key": "AIzaSyC3caYMMidWwczsIAnCZwz7DJmGvYJw3ZA"
        }
      ],
      "services": {
        "appinvite_service": {
          "other_platform_oauth_client": [
            {
              "client_id": "960282246537-t5suv1qklqtea5rghe84lgd9od608a3r.apps.googleusercontent.com",
              "client_type": 3
            }
          ]
        }
      }
    }
  ],
  "configuration_version": "1"
}